{
  "name": "two",
  "compiler": "react",
  "version": "v0.2",
  "type": "app",
  "build": "designer",
  "nextId": 2,
  "rootId": "1",
  "externalCss": [],
  "externalJs": [
    "node_modules/react/dist/react.js",
    "node_modules/react-dom/dist/react-dom.js"
  ],
  "state": {},
  "packages": [
    {
      "name": "react",
      "version": "15.4.2"
    },
    {
      "name": "react-dom",
      "version": "15.4.2"
    }
  ],
  "js": [
    {
      "name": "init",
      "body": "function() { app.render(); }"
    }
  ],
  "cssVars": [],
  "css": [],
  "load": [
    "init"
  ],
  "components": {
    "1": {
      "id": "1",
      "name": "two",
      "element": "div",
      "text": null,
      "attributes": [],
      "css": [],
      "js": [],
      "dynamicAttributes": [],
      "next": null,
      "previous": null,
      "child": null,
      "parent": null
    }
  },
  "filename": "two",
  "pageTitle": "two"
}